goldener/__init__.py
goldener/describe.py
goldener/extract.py
goldener/pxt_utils.py
goldener/reduce.py
goldener/select.py
goldener/split.py
goldener/torch_utils.py
goldener/utils.py
goldener/vectorize.py
goldener-1.1.1.dist-info/licenses/LICENSE
goldener-1.1.1.dist-info/METADATA
goldener-1.1.1.dist-info/WHEEL
goldener-1.1.1.dist-info/top_level.txt
goldener-1.1.1.dist-info/RECORD
