Metadata-Version: 2.4
Name: goldener
Version: 1.1.1
Summary: Goldener - Make your data even more valuable
Author-email: goldener-data <yann.chene.tni@gmail.com>
Project-URL: Homepage, https://github.com/goldener-data/goldener
Project-URL: Repository, https://github.com/goldener-data/goldener
Project-URL: Issues, https://github.com/goldener-data/goldener/issues
Classifier: Development Status :: 4 - Beta
Classifier: Intended Audience :: Developers
Classifier: Intended Audience :: Science/Research
Classifier: Programming Language :: Python :: 3.13
Classifier: Topic :: Scientific/Engineering :: Artificial Intelligence
Requires-Python: >=3.10
License-File: LICENSE
Requires-Dist: torch
Requires-Dist: numpy
Requires-Dist: pixeltable
Requires-Dist: nvidia-ml-py
Requires-Dist: scikit-learn
Requires-Dist: umap-learn
Requires-Dist: torchvision
Requires-Dist: coreax
Requires-Dist: tqdm
Provides-Extra: dev
Requires-Dist: pytest; extra == "dev"
Requires-Dist: pre-commit; extra == "dev"
Requires-Dist: ruff; extra == "dev"
Requires-Dist: mypy; extra == "dev"
Requires-Dist: types-pillow; extra == "dev"
Requires-Dist: types-tqdm; extra == "dev"
Provides-Extra: gpu
Requires-Dist: jax[cuda]; extra == "gpu"
Dynamic: license-file
